imPixelate.py
imPixelate-0.0.2.dist-info/LICENSE
imPixelate-0.0.2.dist-info/METADATA
imPixelate-0.0.2.dist-info/WHEEL
imPixelate-0.0.2.dist-info/top_level.txt
imPixelate-0.0.2.dist-info/RECORD
