Metadata-Version: 2.1
Name: imPixelate
Version: 0.0.2
Summary: This snippet of code attempts to pixelate images.
Home-page: https://github.com/Mamdasn/imPixelate
Author: mamdasn s
Author-email: <mamdassn@gmail.com>
License: UNKNOWN
Keywords: python,histogram,Pixelate,Pixelate Image
Platform: UNKNOWN
Classifier: Development Status :: 1 - Planning
Classifier: Intended Audience :: Science/Research
Classifier: License :: OSI Approved :: MIT License
Classifier: Programming Language :: Python :: 3.8
Classifier: Operating System :: OS Independent
Requires-Dist: numpy
Requires-Dist: numba
